apispec_serpyco/__init__.py
apispec_serpyco/openapi.py
apispec_serpyco/utils.py
apispec_serpyco-0.19.data/data/LICENSE
apispec_serpyco-0.19.dist-info/LICENSE
apispec_serpyco-0.19.dist-info/METADATA
apispec_serpyco-0.19.dist-info/WHEEL
apispec_serpyco-0.19.dist-info/top_level.txt
apispec_serpyco-0.19.dist-info/RECORD
